chemcat/__init__.py
chemcat/network.py
chemcat/version.py
chemcat/data/janaf_conversion.txt
chemcat/data/janaf/Al-001.txt
chemcat/data/janaf/Al-002.txt
chemcat/data/janaf/Al-003.txt
chemcat/data/janaf/Al-004.txt
chemcat/data/janaf/Al-005.txt
chemcat/data/janaf/Al-006.txt
chemcat/data/janaf/Al-007.txt
chemcat/data/janaf/Al-008.txt
chemcat/data/janaf/Al-009.txt
chemcat/data/janaf/Al-010.txt
chemcat/data/janaf/Al-011.txt
chemcat/data/janaf/Al-012.txt
chemcat/data/janaf/Al-013.txt
chemcat/data/janaf/Al-014.txt
chemcat/data/janaf/Al-015.txt
chemcat/data/janaf/Al-016.txt
chemcat/data/janaf/Al-017.txt
chemcat/data/janaf/Al-018.txt
chemcat/data/janaf/Al-019.txt
chemcat/data/janaf/Al-020.txt
chemcat/data/janaf/Al-021.txt
chemcat/data/janaf/Al-022.txt
chemcat/data/janaf/Al-023.txt
chemcat/data/janaf/Al-024.txt
chemcat/data/janaf/Al-025.txt
chemcat/data/janaf/Al-026.txt
chemcat/data/janaf/Al-027.txt
chemcat/data/janaf/Al-028.txt
chemcat/data/janaf/Al-029.txt
chemcat/data/janaf/Al-030.txt
chemcat/data/janaf/Al-031.txt
chemcat/data/janaf/Al-032.txt
chemcat/data/janaf/Al-033.txt
chemcat/data/janaf/Al-034.txt
chemcat/data/janaf/Al-035.txt
chemcat/data/janaf/Al-036.txt
chemcat/data/janaf/Al-037.txt
chemcat/data/janaf/Al-038.txt
chemcat/data/janaf/Al-039.txt
chemcat/data/janaf/Al-040.txt
chemcat/data/janaf/Al-041.txt
chemcat/data/janaf/Al-042.txt
chemcat/data/janaf/Al-043.txt
chemcat/data/janaf/Al-044.txt
chemcat/data/janaf/Al-045.txt
chemcat/data/janaf/Al-046.txt
chemcat/data/janaf/Al-047.txt
chemcat/data/janaf/Al-048.txt
chemcat/data/janaf/Al-049.txt
chemcat/data/janaf/Al-050.txt
chemcat/data/janaf/Al-051.txt
chemcat/data/janaf/Al-052.txt
chemcat/data/janaf/Al-053.txt
chemcat/data/janaf/Al-054.txt
chemcat/data/janaf/Al-055.txt
chemcat/data/janaf/Al-056.txt
chemcat/data/janaf/Al-057.txt
chemcat/data/janaf/Al-058.txt
chemcat/data/janaf/Al-059.txt
chemcat/data/janaf/Al-060.txt
chemcat/data/janaf/Al-061.txt
chemcat/data/janaf/Al-062.txt
chemcat/data/janaf/Al-063.txt
chemcat-0.0.2.dist-info/LICENSE
chemcat-0.0.2.dist-info/METADATA
chemcat-0.0.2.dist-info/WHEEL
chemcat-0.0.2.dist-info/top_level.txt
chemcat-0.0.2.dist-info/RECORD
